metaflow_extensions/slack/plugins/__init__.py
metaflow_extensions/slack/plugins/slack.py
metaflow_slack_notifier-0.1.0.dist-info/METADATA
metaflow_slack_notifier-0.1.0.dist-info/WHEEL
metaflow_slack_notifier-0.1.0.dist-info/licenses/LICENSE.txt
metaflow_slack_notifier-0.1.0.dist-info/RECORD
