Metadata-Version: 2.4
Name: metaflow-slack-notifier
Version: 0.1.0
Summary: Add your description here
Author-email: Kohei Tsuyuki <kotsuyuki@gmail.com>
License: MIT
License-File: LICENSE.txt
Requires-Python: >=3.10
Requires-Dist: metaflow>=2.12
Requires-Dist: requests>=2.0
